{
  "title": "Frictionless Pipeline",
  "$schema": "http://json-schema.org/draft-06/schema#",
  "$id": "https://github.com/frictionlessdata/frictionless-py/tree/master/frictionless/assets/profiles/pipeline.json",
  "type": "object",
  "required": [
    "tasks"
  ],
  "properties": {
    "version": {
      "type": "string",
      "title": "Version",
      "description": "Frictionless version"
    },
    "tasks": {
      "type": "array",
      "title": "Tasks",
      "description": "Pipeline tasks",
      "items": {
        "title": "Task",
        "type": "object",
        "required": ["source", "type", "steps"],
        "properties": {
          "type": {"type": "string", "enum": ["resource", "package"]},
          "steps": {"type": "array"}
        }
      }
    }
  }
}
